Workbook

Sheet Executive Summary
A1: BMW Group (FY 2023)
A3: Revenue: | B3: ='P&L'!E5 -> 155
A4: Automotive EBIT margin: | B4: 0.1
A17: * All data shown in Billion of EUR

Sheet P&L
D5: Revenue | E5: ='Revenue Breakdown'!N7 -> 155 | G5: EBITDA | H5: =E11+'Revenue Breakdown'!B36 -> 30.5
D6: Cost of Sales | E6: =E5 * (1-'Revenue Breakdown'!B31) -> 120.9 | G6: EBIT Margin | H6: =E11/E5 -> 0.10645161
D7: Gross Profit | E7: =E5-E6 -> 34.1 | G7: Net Margin | H7: =E15/E5 -> 0.069625806
D8: Selling & Administrative Expenses | E8: =E5*'Revenue Breakdown'!B32 -> 11.625 | G8: ROI | H8: =E15/125 -> 0.086336
D9: Research & Development Expenses | E9: =E5*'Revenue Breakdown'!B33 -> 6.975 | G9: ROCE | H9: =E11/100 -> 0.165
D10: Other Operating Income / Expenses (net) | E10: ='Revenue Breakdown'!B34 -> 1 | G10: ROE | H10: =E15/'Balance Sheet'!K10 -> 0.16603077
D11: Operating Profit (EBIT) | E11: =E7-E8-E9+E10 -> 16.5
D12: Financial Result | E12: ='Revenue Breakdown'!B35 -> -1.3
D13: Profit Before Tax (EBT) | E13: =E11+E12 -> 15.2
D14: Income Taxes | E14: =E13*'Revenue Breakdown'!B37 -> 4.408
D15: Net Profit | E15: =E13-E14 -> 10.792
D19: * All data shown in Billion of EUR

Sheet Revenue Breakdown
A1: Revenue by Business Segment
A3: Segment \ Month | B3: Jan | C3: Feb | D3: Mar | E3: Apr | F3: May | G3: Jun | H3: Jul | I3: Aug | J3: Sep | K3: Oct | L3: Nov | M3: Dec | N3: FY
A4: Automotive | B4: 9.2 | C4: 9.5 | D4: 11.3 | E4: 10 | F4: 11 | G4: 11.8 | H4: 10.5 | I4: 9.6 | J4: 11.3 | K4: 11.7 | L4: 12.1 | M4: 11.8 | N4: =SUM(B4:M4) -> 129.8
A5: Financial Services | B5: 1.5 | C5: 1.7 | D5: 1.9 | E5: 1.7 | F5: 1.7 | G5: 1.9 | H5: 1.7 | I5: 1.6 | J5: 1.9 | K5: 2 | L5: 2.1 | M5: 1.9 | N5: =SUM(B5:M5) -> 21.6
A6: Motorcycles | B6: 0.3 | C6: 0.3 | D6: 0.3 | E6: 0.3 | F6: 0.3 | G6: 0.3 | H6: 0.3 | I6: 0.3 | J6: 0.3 | K6: 0.3 | L6: 0.3 | M6: 0.3 | N6: =SUM(B6:M6) -> 3.6
A7: Total Revenue | B7: =SUM(B4:B6) -> 11 | C7: =SUM(C4:C6) -> 11.5 | D7: =SUM(D4:D6) -> 13.5 | E7: =SUM(E4:E6) -> 12 | F7: =SUM(F4:F6) -> 13 | G7: =SUM(G4:G6) -> 14 | H7: =SUM(H4:H6) -> 12.5 | I7: =SUM(I4:I6) -> 11.5 | ... N7: =SUM(N4:N6) -> 155
A10: Revenue by Region
A12: Region \ Month | B12: Jan | C12: Feb | D12: Mar | E12: Apr | F12: May | G12: Jun | H12: Jul | I12: Aug | J12: Sep | K12: Oct | L12: Nov | M12: Dec | N12: FY
A13: Europe | B13: 3.8 | C13: 3.9 | D13: 4.6 | E13: 4 | F13: 4.4 | G13: 4.8 | H13: 4.2 | I13: 3.9 | J13: 4.6 | K13: 4.8 | L13: 5 | M13: 4.9 | N13: =SUM(B13:M13) -> 52.9
A14: Asia | B14: 3.3 | C14: 3.4 | D14: 4.1 | E14: 3.6 | F14: 3.8 | G14: 4.2 | H14: 3.8 | I14: 3.5 | J14: 4.1 | K14: 4.2 | L14: 4.4 | M14: 4.2 | N14: =SUM(B14:M14) -> 46.6
A15: Americas | B15: 3.1 | C15: 3.3 | D15: 3.8 | E15: 3.4 | F15: 3.7 | G15: 3.9 | H15: 3.5 | I15: 3.2 | J15: 3.7 | K15: 3.9 | L15: 4 | M15: 3.8 | N15: =SUM(B15:M15) -> 43.3
A16: Other regions | B16: 0.8 | C16: 0.9 | D16: 1 | E16: 1 | F16: 1.1 | G16: 1.1 | H16: 1 | I16: 0.9 | J16: 1.1 | K16: 1.1 | L16: 1.1 | M16: 1.1 | N16: =SUM(B16:M16) -> 12.2
A17: Total Revenue | B17: =SUM(B13:B16) -> 11 | C17: =SUM(C13:C16) -> 11.5 | D17: =SUM(D13:D16) -> 13.5 | E17: =SUM(E13:E16) -> 12 | F17: =SUM(F13:F16) -> 13 | G17: =SUM(G13:G16) -> 14 | H17: =SUM(H13:H16) -> 12.5 | I17: =SUM(I13:I16) -> 11.5 | ... N17: =SUM(N13:N16) -> 155
A20: Automotive Revenue by Product Type
A22: Product \ Month | B22: Jan | C22: Feb | D22: Mar | E22: Apr | F22: May | G22: Jun | H22: Jul | I22: Aug | J22: Sep | K22: Oct | L22: Nov | M22: Dec | N22: FY
A23: ICE Vehicles | B23: 7.2 | C23: 7.4 | D23: 8.7 | E23: 7.8 | F23: 8.4 | G23: 9 | H23: 8.1 | I23: 7.3 | J23: 8.7 | K23: 9 | L23: 9.3 | M23: 9.1 | N23: =SUM(B23:M23) -> 100
A24: Electric / Hybrid | B24: 1.4 | C24: 1.5 | D24: 1.9 | E24: 1.6 | F24: 1.9 | G24: 2.1 | H24: 1.8 | I24: 1.7 | J24: 1.9 | K24: 2 | L24: 2.1 | M24: 2 | N24: =SUM(B24:M24) -> 21.9
A25: MINI & Compact | B25: 0.6 | C25: 0.6 | D25: 0.7 | E25: 0.6 | F25: 0.7 | G25: 0.7 | H25: 0.6 | I25: 0.6 | J25: 0.7 | K25: 0.7 | L25: 0.7 | M25: 0.7 | N25: =SUM(B25:M25) -> 7.9
A26: Total Automotive | B26: =SUM(B23:B25) -> 9.2 | C26: =SUM(C23:C25) -> 9.5 | D26: =SUM(D23:D25) -> 11.3 | E26: =SUM(E23:E25) -> 10 | F26: =SUM(F23:F25) -> 11 | G26: =SUM(G23:G25) -> 11.8 | H26: =SUM(H23:H25) -> 10.5 | I26: =SUM(I23:I25) -> 9.6 | ... N26: =SUM(N23:N25) -> 129.8
A29: Assumptions
A31: Gross Margin: | B31: 0.22
A32: SG&A: | B32: 0.075
A33: R&D: | B33: 0.045
A34: Other Operating: | B34: 1
A35: Financial Result: | B35: -1.3
A36: D&A | B36: ='Cash Flow'!D6 -> 14
A37: Tax Rate: | B37: 0.29
A40: * All data shown in Billion of EUR

Sheet Cash Flow
C3: CFO | E3: CFI | G3: CFF
C5: Net Profit | D5: ='P&L'!E15 -> 10.792 | E5: Capital Expenditures (CapEx) | F5: 17 | G5: Dividends Paid | H5: 6
C6: Depreciation & Amortization | D6: 14 | G6: Net Debt Repayment | H6: 1.5
C7: Change in Working Capital | D7: =('Balance Sheet'!F7+'Balance Sheet'!F8-'Balance Sheet'!O7)/12 -> 3.1666667
C8: NET CASH CFO | D8: =SUM(D5:D6)-D7 -> 21.625333 | E8: NET CASH CFI | F8: =F5 -> 17 | G8: NET CASH CFF | H8: =SUM(H5:H6) -> 7.5
C9: NET CHANGE CASH
C10: =D8-F8-H8 -> -2.8746667
C14: * All data shown in Billion of EUR

Sheet Balance Sheet
C3: ASSETS | J3: EQUITY & LIABILITIES
C5: Non-current Assets | E5: Current Assets | J5: Equity | L5: Non-current Liabilities | N5: Current Liabilities
C7: Property, Plant & Equipment (PPE) | D7: 95 | E7: Inventory | F7: 42 | J7: Share Capital | K7: 10 | L7: Long-term Debt | M7: 95 | N7: Trade Payables | O7: 31
C8: Intangible Assets | D8: 30 | E8: Trade Receivables | F8: 27 | J8: Retained Earnings | K8: 45 | L8: Pension & Provisions | M8: 35 | N8: Short-term Debt | O8: 3
C9: Other non-current assets | D9: 20 | E9: Cash & Cash Equivalents | F9: 13 | J9: Other equity | K9: 10 | L9: Other long-term liabilities | M9: 15 | N9: Other current liabilities | O9: 1
E10: Other current assets | F10: 18 | K10: =SUM(K7:K9) -> 65 | M10: =SUM(M7:M9) -> 145 | O10: =SUM(O7:O9) -> 35
D11: =SUM(D7:D9) -> 145 | F11: =SUM(F7:F10) -> 100 | J11: =SUM(K10:O10) -> 245
C12: =SUM(D11,F11) -> 245
C16: * All data shown in Billion of EUR
