Workbook

Sheet Main
A1: IKEA
A3: IKEA is a global home-furnishing retailer operating under a cost-leadership and scale-driven model. The company focuses on delivering affordable lifestyle solutions through vertical integration, high inventory turnover, self-service formats, and optimized logistics. Unlike premium manufacturers, IKEA’s competitive advantage is built on operational efficiency rather than product margin expansion.
A6: Revenue: | D6: ='P&L'!B1 -> 50.45
A7: EBIT Margin: | D7: =KPI!B2 -> 0.090946482
A8: Net Profit: | D8: ='P&L'!B11 -> 3.266835
A9: Free Cash Flow: | D9: =CF!C9-CF!E6 -> 9.766835

Sheet P&L
A1: Revenue | B1: =Revenue!N8 -> 50.45
A2: Cost of Sales | B2: =B1 * (1-Assumptions!B4) -> 33.297
A3: Gross Profit | B3: =B1-B2 -> 17.153
A4: Selling & Administrative Expenses | B4: =B1*Assumptions!B5 -> 12.108
A5: Research & Development Expenses | B5: =B1*Assumptions!B6 -> 0.75675
A6: Other Operating Income / Expenses (net) | B6: 0.3
A7: Operating Profit (EBIT) | B7: =B3-B4-B5+B6 -> 4.58825
A8: Financial Result | B8: -0.4
A9: Profit Before Tax (EBT) | B9: =B7+B8 -> 4.18825
A10: Income Taxes | B10: =B9*Assumptions!B8 -> 0.921415
A11: Net Profit | B11: =B9-B10 -> 3.266835

Sheet KPI
A1: EBITDA | B1: ='P&L'!B7+'P&L'!B1*Assumptions!B7 -> 7.8675
A2: EBIT Margin | B2: ='P&L'!B7/'P&L'!B1 -> 0.090946482
A3: Net Margin | B3: ='P&L'!B11/'P&L'!B1 -> 0.064753915
A4: ROI | B4: ='P&L'!B1/200 -> 0.25225
A5: ROCE | B5: ='P&L'!B1/121 -> 0.41694215
A6: ROE | B6: ='P&L'!B11/BS!I8 -> 0.1306734

Sheet BS
A1: ASSETS | H1: EQUITY & LIABILITIES
A3: Non-current Assets | C3: Current Assets | H3: Equity | J3: Non-current Liabilities | L3: Current Liabilities
A5: Property, Plant & Equipment (PPE) | B5: 32 | C5: Inventory | D5: 14 | H5: Share Capital | I5: 5 | J5: Long-term Debt | K5: 22 | L5: Trade Payables | M5: 14
A6: Intangible Assets | B6: 9 | C6: Trade Receivables | D6: 4 | H6: Retained Earnings | I6: 18 | J6: Pension & Provisions | K6: 8 | L6: Short-term Debt | M6: 2
A7: Other non-current assets | B7: 6 | C7: Cash & Cash Equivalents | D7: 8 | H7: Other equity | I7: 2 | J7: Other long-term liabilities | K7: 5 | L7: Other current liabilities | M7: 2
C8: Other current assets | D8: 5 | I8: =SUM(I5:I7) -> 25 | K8: =SUM(K5:K7) -> 35 | M8: =SUM(M5:M7) -> 18
B9: =SUM(B5:B7) -> 47 | D9: =SUM(D5:D8) -> 31 | H9: =SUM(I8:M8) -> 78
A10: =SUM(B9,D9) -> 78

Sheet CF
B4: CFO | D4: CFI | F4: CFF
B6: Net Profit | C6: ='P&L'!B11 -> 3.266835 | D6: Capital Expenditures (CapEx) | E6: 3.5 | F6: Dividends Paid | G6: 2
B7: Depreciation & Amortization | C7: 14 | F7: Net Debt Repayment | G7: 0.5
B8: Change in Working Capital | C8: =BS!D5+BS!D6-BS!M5 -> 4
B9: NET CASH CFO | C9: =SUM(C6:C7)-C8 -> 13.266835 | D9: NET CASH CFI | E9: =E6 -> 3.5 | F9: NET CASH CFF | G9: =SUM(G6:G7) -> 2.5

Sheet Revenue
B2: Jan | C2: Feb | D2: Mar | E2: Apr | F2: May | G2: Jun | H2: Jul | I2: Aug | J2: Sep | K2: Oct | L2: Nov | M2: Dec | N2: FY
A3: Furniture (Living, Bedroom, Office) | B3: 1.95 | C3: 2.05 | D3: 2.4 | E3: 2.65 | F3: 2.85 | G3: 2.95 | H3: 2.8 | I3: 2.55 | J3: 2.45 | K3: 2.55 | L3: 2.7 | M3: 2.85 | N3: =SUM(B3:M3) -> 30.75
A4: Home Accessories & Décor | B4: 0.55 | C4: 0.6 | D4: 0.7 | E4: 0.75 | F4: 0.85 | G4: 0.9 | H4: 0.85 | I4: 0.75 | J4: 0.7 | K4: 0.75 | L4: 0.8 | M4: 0.9 | N4: =SUM(B4:M4) -> 9.1
A5: Kitchen & Home Appliances | B5: 0.4 | C5: 0.45 | D5: 0.5 | E5: 0.5 | F5: 0.55 | G5: 0.6 | H5: 0.55 | I5: 0.45 | J5: 0.4 | K5: 0.45 | L5: 0.5 | M5: 0.48 | N5: =SUM(B5:M5) -> 5.83
A6: Services (Delivery, Assembly, Installation) | B6: 0.2 | C6: 0.2 | D6: 0.22 | E6: 0.24 | F6: 0.26 | G6: 0.28 | H6: 0.26 | I6: 0.24 | J6: 0.23 | K6: 0.25 | L6: 0.28 | M6: 0.26 | N6: =SUM(B6:M6) -> 2.92
A7: B2B & Contract Sales | B7: 0.1 | C7: 0.1 | D7: 0.13 | E7: 0.16 | F7: 0.18 | G7: 0.2 | H7: 0.18 | I7: 0.16 | J7: 0.15 | K7: 0.16 | L7: 0.17 | M7: 0.16 | N7: =SUM(B7:M7) -> 1.85
A8: Total Revenue | B8: =SUM(B3:B7) -> 3.2 | C8: =SUM(C3:C7) -> 3.4 | D8: =SUM(D3:D7) -> 3.95 | E8: =SUM(E3:E7) -> 4.3 | F8: =SUM(F3:F7) -> 4.69 | G8: =SUM(G3:G7) -> 4.93 | H8: =SUM(H3:H7) -> 4.64 | I8: =SUM(I3:I7) -> 4.15 | ... N8: =SUM(N3:N7) -> 50.45

Sheet Assumptions
A2: Assumptions
A4: Gross Margin: | B4: 0.34
A5: SG&A: | B5: 0.24
A6: R&D: | B6: 0.015
A7: D&A | B7: =0.065 -> 0.065
A8: Tax Rate: | B8: 0.22
